pr_lint/__init__.py
pr_lint/formatter.py
pr_lint/linter.py
pr_lint/main.py
pr_lint/py.typed
pr_lint/utils.py
pr_lint-0.5.dist-info/LICENSE
pr_lint-0.5.dist-info/METADATA
pr_lint-0.5.dist-info/WHEEL
pr_lint-0.5.dist-info/entry_points.txt
pr_lint-0.5.dist-info/RECORD
