Metadata-Version: 2.1
Name: pr-lint
Version: 0.5
Summary: 
Author: lucemia
Author-email: lucemia@gmail.com
Requires-Python: >=3.10,<4.0
Classifier: Programming Language :: Python :: 3
Classifier: Programming Language :: Python :: 3.10
Classifier: Programming Language :: Python :: 3.11
Classifier: Programming Language :: Python :: 3.12
Requires-Dist: pygithub
Requires-Dist: typer
